notebook_xterm/__init__.py
notebook_xterm/terminalclient.js
notebook_xterm/terminalserver.py
notebook_xterm/xterm.py
notebook_xterm-0.2.0.dist-info/DESCRIPTION.rst
notebook_xterm-0.2.0.dist-info/METADATA
notebook_xterm-0.2.0.dist-info/RECORD
notebook_xterm-0.2.0.dist-info/WHEEL
notebook_xterm-0.2.0.dist-info/metadata.json
notebook_xterm-0.2.0.dist-info/top_level.txt
