Metadata-Version: 2.0
Name: notebook-xterm
Version: 0.2.0
Summary: A fully-functional terminal emulator in a Jupyter notebook.
Home-page: http://github.com/adamj9431/notebook_xterm
Author: Adam Johnson
Author-email: adam.johnson@us.ibm.com
License: MIT
Keywords: Jupyter xterm notebook terminal bash shell cli
Platform: UNKNOWN
Requires-Dist: future
